transferhub/__init__.py
transferhub/client.py
transferhub-0.0.1.dist-info/WHEEL
transferhub-0.0.1.dist-info/METADATA
transferhub-0.0.1.dist-info/RECORD
