Metadata-Version: 2.1
Name: transferhub
Version: 0.0.1
Summary: 
Author: JanSeidlein
Author-email: jan@dmesh.io
Requires-Python: >=3.6.1,<4.0.0
Classifier: Programming Language :: Python :: 3
Classifier: Programming Language :: Python :: 3.7
Classifier: Programming Language :: Python :: 3.8
Classifier: Programming Language :: Python :: 3.9
Requires-Dist: requests (>=2.26.0,<3.0.0)
